pydar/__init__.py
pydar/display_image.py
pydar/error_handling.py
pydar/extract_flyby_parameters.py
pydar/read_readme.py
pydar/retrieve_ids_by_time_position.py
pydar/updateCsvCORADRJPLOptions.py
pydar/updateCsvFeatureNameDetails.py
pydar/updateCsvSwathCoverage.py
pydar/data/cassini_flyby.csv
pydar/data/coradr_jpl_options.csv
pydar/data/feature_name_details.csv
pydar/data/sar_swath_details.csv
pydar/data/swath_coverage_by_time_position.csv
pydar-2.0.1.dist-info/licenses/LICENSE
pydar-2.0.1.dist-info/METADATA
pydar-2.0.1.dist-info/WHEEL
pydar-2.0.1.dist-info/top_level.txt
pydar-2.0.1.dist-info/RECORD
