Metadata-Version: 2.4
Name: pydar
Version: 2.0.1
Summary: A Python package to access, download, view, and manipulate Cassini RADAR images
Author-email: Cora Schneck <cyschneck@gmail.com>, Una Schneck <ugschneck@gmail.com>
License: MIT License
Project-URL: Repository, https://github.com/unaschneck/pydar
Project-URL: Issues, https://github.com/unaschneck/pydar/issues
Keywords: geophysics,python,astronomy,nasa,radar,planetary-science,cassini,jpl
Classifier: Development Status :: 4 - Beta
Classifier: Intended Audience :: Developers
Classifier: Intended Audience :: Education
Classifier: Intended Audience :: Science/Research
Classifier: License :: OSI Approved :: MIT License
Classifier: Programming Language :: Python
Classifier: Programming Language :: Python :: 3
Classifier: Programming Language :: Python :: 3.10
Classifier: Programming Language :: Python :: 3.11
Classifier: Programming Language :: Python :: 3.12
Classifier: Programming Language :: Python :: 3.13
Classifier: Intended Audience :: Education
Classifier: Intended Audience :: Science/Research
Classifier: Topic :: Scientific/Engineering :: Physics
Classifier: Topic :: Scientific/Engineering :: Image Processing
Classifier: Topic :: Scientific/Engineering :: Visualization
Classifier: Topic :: Scientific/Engineering :: Astronomy
Requires-Python: >=3.10
License-File: LICENSE
Requires-Dist: beautifulsoup4
Requires-Dist: matplotlib
Requires-Dist: pandas
Requires-Dist: pdr
Requires-Dist: pyproj
Requires-Dist: rasterio
Requires-Dist: urllib3
Provides-Extra: dev
Requires-Dist: pytest; extra == "dev"
Requires-Dist: pre-commit; extra == "dev"
Dynamic: license-file
